README.md
setup.py
pubeasy/__init__.py
pubeasy/collection.py
pubeasy/pubeasy.py
pubeasy.egg-info/PKG-INFO
pubeasy.egg-info/SOURCES.txt
pubeasy.egg-info/dependency_links.txt
pubeasy.egg-info/not-zip-safe
pubeasy.egg-info/top_level.txt
pubeasy/fonts/cmunbx.ttf
pubeasy/fonts/cmunrm.ttf
pubeasy/fonts/cmunti.ttf